LICENSE
MANIFEST.in
README.rst
setup.py
tempi/__init__.py
tempi/main.py
tempi.egg-info/PKG-INFO
tempi.egg-info/SOURCES.txt
tempi.egg-info/dependency_links.txt
tempi.egg-info/entry_points.txt
tempi.egg-info/not-zip-safe
tempi.egg-info/requires.txt
tempi.egg-info/top_level.txt