Metadata-Version: 1.1
Name: tempi
Version: 0.2.1
Summary: Add tempo metadata to your music collection.
Home-page: https://github.com/lmacken/tempi
Author: Luke Macken
Author-email: lmacken@redhat.com
License: GPLv3
Keywords: music tempo bpm echonest
Platform: UNKNOWN
Classifier: Topic :: Multimedia :: Sound/Audio :: Analysis
